Metadata-Version: 2.1
Name: python-espeak-ng
Version: 0.6.6
Summary: Python C extension for the eSpeak NG speech synthesizer
Home-page: https://github.com/asrp/python-espeak
Author: Siegfried-A. Gevatter Pujals, asrp
Author-email: asrp@email.com
License: GNU GPL
Platform: posix
